unificontroller/__init__.py
unificontroller/class_unificontroller.py
unificontroller-1.0.0.dist-info/METADATA
unificontroller-1.0.0.dist-info/WHEEL
unificontroller-1.0.0.dist-info/licenses/LICENSE.txt
unificontroller-1.0.0.dist-info/RECORD
